pyhydroqc/__init__.py
pyhydroqc/anomaly_utilities.py
pyhydroqc/arima_correct.py
pyhydroqc/calibration.py
pyhydroqc/model_workflow.py
pyhydroqc/modeling_utilities.py
pyhydroqc/parameters.py
pyhydroqc/rules_detect.py
pyhydroqc-0.0.4.dist-info/LICENSE
pyhydroqc-0.0.4.dist-info/METADATA
pyhydroqc-0.0.4.dist-info/WHEEL
pyhydroqc-0.0.4.dist-info/top_level.txt
pyhydroqc-0.0.4.dist-info/RECORD
