Metadata-Version: 2.1
Name: pyhydroqc
Version: 0.0.4
Summary: A package containing functions for anomaly detection and correction of aquatic sensor data.
Home-page: https://github.com/AmberSJones/pyhydroqc
Author: Amber Jones
Author-email: amber.jones@usu.edu
License: UNKNOWN
Platform: UNKNOWN
Classifier: Programming Language :: Python :: 3
Classifier: Development Status :: 4 - Beta
Classifier: License :: OSI Approved :: BSD License
Classifier: Operating System :: OS Independent
Classifier: Intended Audience :: Science/Research
Classifier: Topic :: Scientific/Engineering :: Hydrology
Requires-Python: >=3.6
License-File: LICENSE
Requires-Dist: sklearn
Requires-Dist: tensorflow
Requires-Dist: matplotlib
Requires-Dist: scipy
Requires-Dist: pmdarima
Requires-Dist: statsmodels
Requires-Dist: numpy
Requires-Dist: pandas
